setup.py
pn_probability/Binomialdistribution.py
pn_probability/Gaussiandistribution.py
pn_probability/Generaldistribution.py
pn_probability/__init__.py
pn_probability.egg-info/PKG-INFO
pn_probability.egg-info/SOURCES.txt
pn_probability.egg-info/dependency_links.txt
pn_probability.egg-info/not-zip-safe
pn_probability.egg-info/top_level.txt