Metadata-Version: 1.0
Name: pn-probability
Version: 0.1
Summary: Gaussian and Binomial distributions
Home-page: UNKNOWN
Author: Kefah Khalil
Author-email: kefahstudent2018@gmail.com
License: UNKNOWN
Platform: UNKNOWN
